MANIFEST.in
README.rst
classifiers.txt
requirements.txt
setup.py
version.txt
rdc/__init__.py
rdc.common.egg-info/PKG-INFO
rdc.common.egg-info/SOURCES.txt
rdc.common.egg-info/dependency_links.txt
rdc.common.egg-info/namespace_packages.txt
rdc.common.egg-info/requires.txt
rdc.common.egg-info/top_level.txt
rdc/common/__init__.py
rdc/common/test/__init__.py
rdc/common/util/__init__.py
rdc/common/util/text.py